beginning_package/__init__.py
beginning_package/main.py
beginning_package-0.0.1.dist-info/METADATA
beginning_package-0.0.1.dist-info/WHEEL
beginning_package-0.0.1.dist-info/licenses/LICENSE
beginning_package-0.0.1.dist-info/RECORD
