Metadata-Version: 2.3
Name: beginning_package
Version: 0.0.1
Summary: My first library
Project-URL: Homepage, https://github.com/freekopik/test/
Project-URL: Issues, https://github.com/freekopik/test/issues
Author-email: freekopik <akkoficialnyj1@gmail.com>
License-File: LICENSE
Classifier: License :: OSI Approved :: MIT License
Classifier: Operating System :: OS Independent
Classifier: Programming Language :: Python :: 3
Requires-Python: >=3.10.0
